pywinEA/__init__.py
pywinEA/version.py
pywinEA/algorithm/__init__.py
pywinEA/algorithm/_algorithm_init.py
pywinEA/algorithm/basic.py
pywinEA/algorithm/nsga2.py
pywinEA/algorithm/spea2.py
pywinEA/dataset/__init__.py
pywinEA/dataset/load_demo.py
pywinEA/dataset/data/BreastCancerWisconsin.csv
pywinEA/error/__init__.py
pywinEA/error/exceptions.py
pywinEA/fitness/__init__.py
pywinEA/fitness/objective.py
pywinEA/imputation/__init__.py
pywinEA/imputation/dynamic.py
pywinEA/imputation/estimator.py
pywinEA/imputation/fixed.py
pywinEA/interface/__init__.py
pywinEA/interface/_algorithm_init.py
pywinEA/interface/algorithm.py
pywinEA/interface/fitness.py
pywinEA/interface/imputation.py
pywinEA/interface/operators.py
pywinEA/interface/wrapper.py
pywinEA/operators/__init__.py
pywinEA/operators/individual.py
pywinEA/operators/population.py
pywinEA/population/__init__.py
pywinEA/population/population.py
pywinEA/population/representation.py
pywinEA/utils/__init__.py
pywinEA/utils/fast_non_dominated_sort.py
pywinEA/utils/hypervolume.py
pywinEA/visualization/__init__.py
pywinEA/visualization/evaluation.py
pywinEA/visualization/evolution.py
pywinEA/wrapper/__init__.py
pywinEA/wrapper/wrapper.py
pywinEA-0.0.2.dist-info/LICENSE
pywinEA-0.0.2.dist-info/METADATA
pywinEA-0.0.2.dist-info/WHEEL
pywinEA-0.0.2.dist-info/top_level.txt
pywinEA-0.0.2.dist-info/RECORD
