Metadata-Version: 2.1
Name: pywinEA
Version: 0.0.2
Summary: Package with basic implementations of mono and multi-objective genetic algorithms for feature selection.
Home-page: https://github.com/FernandoGaGu/pywinEA
Author: Fernando Garcia
Author-email: fernando.garciagu@alumnos.upm.es
License: MIT
Platform: UNKNOWN
Classifier: Programming Language :: Python :: 3
Classifier: License :: OSI Approved :: MIT License
Requires-Python: >=3.6
Requires-Dist: numpy
Requires-Dist: sklearn
Requires-Dist: tqdm
Requires-Dist: pandas
Requires-Dist: matplotlib
